MANIFEST.in
README.md
setup.cfg
setup.py
class4gl/Equirectangular_projection_SW.png
class4gl/__init__.py
class4gl/base_shr_efera5.png
class4gl/class4gl.py
class4gl/data_global.py
class4gl/data_soundings.py
class4gl/era_advection.py
class4gl/interface_functions.py
class4gl/interface_functions_ruby.py
class4gl/interface_multi.py
class4gl/model.py
class4gl/model_ent.py
class4gl/model_ent2.py
class4gl/model_git.py
class4gl.egg-info/PKG-INFO
class4gl.egg-info/SOURCES.txt
class4gl.egg-info/dependency_links.txt
class4gl.egg-info/requires.txt
class4gl.egg-info/top_level.txt
class4gl/analysis/evalflux_GOAMAZON.py
class4gl/analysis/evalflux_GOAMAZON_corr.py
class4gl/interface/base_global.png
class4gl/interface/base_global_erai.png
class4gl/interface/base_global_gleam.png
class4gl/interface/base_global_taylor.png
class4gl/interface/interface.py
class4gl/interface/interface_cloudiness.py
class4gl/interface/interface_for_brecht.py
class4gl/interface/interface_koeppen.py
class4gl/interface/interface_new_koeppen.py
class4gl/interface/interface_show_profiles.py
class4gl/interface/interface_show_profiles_all.py
class4gl/interface/interface_show_profiles_goamazon.py
class4gl/interface/interface_show_profiles_goamazon_copy.py
class4gl/interface/interface_show_profiles_goamazon_corr.py
class4gl/interface/interface_stations.py
class4gl/interface/taylorDiagram.py
class4gl/interface/taylor_global.png
class4gl/interface/test.test
class4gl/interface/test_histogram.py
class4gl/interface/world_histogram.py
class4gl/processing/batch_update_output.py
class4gl/processing/update_output.py
class4gl/ribtol/Makefile
class4gl/ribtol/MakefileMac
class4gl/ribtol/__init__.py
class4gl/ribtol/ribtol.cpp
class4gl/ribtol/ribtol.pyx
class4gl/ribtol/ribtol_hw.py
class4gl/ribtol/setup.py
class4gl/setup/batch_setup_era.pbs
class4gl/setup/batch_setup_era.py
class4gl/setup/batch_setup_global_old.py
class4gl/setup/batch_setup_igra.pbs
class4gl/setup/batch_setup_igra.py
class4gl/setup/batch_update.py
class4gl/setup/batch_update_input.py
class4gl/setup/parsers.py
class4gl/setup/setup_bllast.py
class4gl/setup/setup_bllast_noon.py
class4gl/setup/setup_era.py
